Metadata-Version: 2.4
Name: textpy_llm
Version: 0.1.4
Summary: TextPy: Collaborative Agent Workflow through Programming and Prompting
Author-email: Zhengmao Ye <yezhengmaolove@gmail.com>
Maintainer-email: Zhengmao Ye <yezhengmaolove@gmail.com>
Requires-Python: >=3.12
Requires-Dist: litellm==1.67.5
